pelican/plugins/minification/__init__.py
pelican_minification-1.0.1.dist-info/LICENSE
pelican_minification-1.0.1.dist-info/METADATA
pelican_minification-1.0.1.dist-info/WHEEL
pelican_minification-1.0.1.dist-info/top_level.txt
pelican_minification-1.0.1.dist-info/RECORD
